{
  "generatedAt": "2026-07-16T03:20:17.701Z",
  "totalCompanies": 0,
  "totalDisclosures": 0,
  "categories": {
    "nameChanges": [],
    "majorHolderChanges": [],
    "lawsuits": [],
    "cbIssuances": [],
    "capitalChanges": []
  },
  "companies": {},
  "dailyReport": {
    "highRiskCount": 6,
    "totalSignals": 34,
    "topRisks": [
      {
        "name": "이렘",
        "score": 65,
        "signals": [
          "증자/감자",
          "상장폐지위험"
        ]
      },
      {
        "name": "이화산업",
        "score": 60,
        "signals": [
          "대주주변경"
        ]
      },
      {
        "name": "조일알미늄",
        "score": 60,
        "signals": [
          "대주주변경"
        ]
      },
      {
        "name": "육일씨엔에쓰",
        "score": 35,
        "signals": [
          "상장폐지위험"
        ]
      },
      {
        "name": "인산가",
        "score": 35,
        "signals": [
          "상장폐지위험"
        ]
      },
      {
        "name": "한탑",
        "score": 35,
        "signals": [
          "상장폐지위험"
        ]
      }
    ]
  }
}